_auto_run_with_pytest/__init__.py
emtest/__init__.py
emtest/func_utils.py
emtest/log_recording.py
emtest/log_utils.py
emtest/pytest_utils.py
emtest/testing_utils.py
emtest-0.0.10.dist-info/licenses/LICENSE
emtest-0.0.10.dist-info/licenses/LICENSE-CC0
emtest-0.0.10.dist-info/METADATA
emtest-0.0.10.dist-info/WHEEL
emtest-0.0.10.dist-info/top_level.txt
emtest-0.0.10.dist-info/RECORD
