Metadata-Version: 2.4
Name: emtest
Version: 0.0.10
Summary: Testing utilities which I find useful.
Author-email: Emendir <dev@emendir.tech>
License-Expression: MIT-0 OR CC0-1.0
Classifier: Programming Language :: Python :: 3
Classifier: Operating System :: OS Independent
Requires-Python: >=3.6
License-File: LICENSE
License-File: LICENSE-CC0
Requires-Dist: appdirs
Requires-Dist: environs
Requires-Dist: pytest
Requires-Dist: termcolor
Requires-Dist: tqdm
Dynamic: license-file
